PCRegression.py
PCRegression-0.1.1.dist-info/DESCRIPTION.rst
PCRegression-0.1.1.dist-info/METADATA
PCRegression-0.1.1.dist-info/RECORD
PCRegression-0.1.1.dist-info/WHEEL
PCRegression-0.1.1.dist-info/metadata.json
PCRegression-0.1.1.dist-info/top_level.txt
