Metadata-Version: 2.0
Name: PCRegression
Version: 0.1.1
Summary: Python package for building a principal components regression model using scikit-learn
Home-page: https://github.com/manojkarthick/PCRegression
Author: Karanjit Singh Tiwana, Arin Ghosh, Manoj Karthick
Author-email: manojkarthick@ymail.com
License: MIT License
Keywords: machine learning,sklearn,pcr,pca,regression,dimensionality reduction
Platform: UNKNOWN
Classifier: Development Status :: 4 - Beta
Classifier: Intended Audience :: Developers
Classifier: License :: OSI Approved :: MIT License
Classifier: Programming Language :: Python :: 3
Classifier: Programming Language :: Python :: 3.2
Classifier: Programming Language :: Python :: 3.3
Classifier: Programming Language :: Python :: 3.4
Classifier: Programming Language :: Python :: 3.5
Classifier: Programming Language :: Python :: 3.6
Requires-Dist: numpy (>=1.8.2)
Requires-Dist: scikit-learn
Requires-Dist: scipy (>=0.13.3)
